.gitignore
CHANGES.rst
CONTRIBUTORS.rst
README.rst
bootstrap.py
buildout.cfg
setup.py
docs/LICENSE.GPL
docs/LICENSE.txt
src/vs/__init__.py
src/vs.bootstrap.tinymce.egg-info/PKG-INFO
src/vs.bootstrap.tinymce.egg-info/SOURCES.txt
src/vs.bootstrap.tinymce.egg-info/dependency_links.txt
src/vs.bootstrap.tinymce.egg-info/entry_points.txt
src/vs.bootstrap.tinymce.egg-info/namespace_packages.txt
src/vs.bootstrap.tinymce.egg-info/not-zip-safe
src/vs.bootstrap.tinymce.egg-info/requires.txt
src/vs.bootstrap.tinymce.egg-info/top_level.txt
src/vs/bootstrap/__init__.py
src/vs/bootstrap/tinymce/__init__.py
src/vs/bootstrap/tinymce/configure.zcml
src/vs/bootstrap/tinymce/testing.py
src/vs/bootstrap/tinymce/testing.zcml
src/vs/bootstrap/tinymce/profiles/default/metadata.xml
src/vs/bootstrap/tinymce/profiles/default/tinymce.xml
src/vs/bootstrap/tinymce/profiles/testing/metadata.xml
src/vs/bootstrap/tinymce/tests/__init__.py
src/vs/bootstrap/tinymce/tests/test_setup.py