Metadata-Version: 1.1
Name: vs.bootstrap.tinymce
Version: 1.0.3
Summary: Bootstrap css classes for TinyMCE
Home-page: https://github.com/veit/vs.bootstrap.tinymce
Author: Veit Schiele
Author-email: kontakt@veit-schiele.de
License: GPL version 2
Keywords: plone tinymce bootstrap
Platform: UNKNOWN
Classifier: Environment :: Web Environment
Classifier: Framework :: Plone
Classifier: Operating System :: OS Independent
Classifier: Programming Language :: Python
Classifier: Programming Language :: Python :: 2.6
Classifier: Topic :: Software Development :: Libraries :: Python Modules
